{
  "as_of_ist": "2026-02-07T04:51:21.063836Z",
  "universe": "NIFTY50",
  "method": "momentum + volume (stable fallback)",
  "picks": [
    {
      "ticker": "IOC.NS",
      "close": 175.2,
      "ret5": 0.0733,
      "vol_surge": 2.44,
      "rsi14": 50.0,
      "score": 0.2216
    },
    {
      "ticker": "ITC.NS",
      "close": 325.8,
      "ret5": 0.0325,
      "vol_surge": 2.72,
      "rsi14": 50.0,
      "score": 0.2075
    },
    {
      "ticker": "POWERGRID.NS",
      "close": 292.75,
      "ret5": 0.1413,
      "vol_surge": 1.11,
      "rsi14": 50.0,
      "score": 0.1869
    },
    {
      "ticker": "ADANIPORTS.NS",
      "close": 1550.7,
      "ret5": 0.0922,
      "vol_surge": 1.41,
      "rsi14": 50.0,
      "score": 0.1679
    },
    {
      "ticker": "BHARTIARTL.NS",
      "close": 2038.4,
      "ret5": 0.0354,
      "vol_surge": 2.09,
      "rsi14": 50.0,
      "score": 0.1677
    }
  ]
}