{
  "as_of_ist": "2025-08-14T04:03:45.107605Z",
  "universe": "NIFTY50",
  "method": "momentum + volume (stable fallback)",
  "picks": [
    {
      "ticker": "BPCL.NS",
      "close": 323.15,
      "ret5": 0.0412,
      "vol_surge": 0.58,
      "rsi14": 50.0,
      "score": 0.0718
    },
    {
      "ticker": "HDFCLIFE.NS",
      "close": 787.55,
      "ret5": 0.0421,
      "vol_surge": 0.23,
      "rsi14": 50.0,
      "score": 0.0491
    },
    {
      "ticker": "CIPLA.NS",
      "close": 1572.0,
      "ret5": 0.0543,
      "vol_surge": 0.05,
      "rsi14": 50.0,
      "score": 0.0469
    },
    {
      "ticker": "DRREDDY.NS",
      "close": 1262.5,
      "ret5": 0.0514,
      "vol_surge": 0.06,
      "rsi14": 50.0,
      "score": 0.0453
    },
    {
      "ticker": "INFY.NS",
      "close": 1449.2,
      "ret5": 0.0086,
      "vol_surge": 0.31,
      "rsi14": 50.0,
      "score": 0.0276
    }
  ]
}