{
  "as_of_ist": "2025-08-20T03:52:32.780595Z",
  "universe": "NIFTY50",
  "method": "momentum + volume (stable fallback)",
  "picks": [
    {
      "ticker": "MARUTI.NS",
      "close": 14272.0,
      "ret5": 0.1115,
      "vol_surge": 0.15,
      "rsi14": 50.0,
      "score": 0.0992
    },
    {
      "ticker": "HEROMOTOCO.NS",
      "close": 5126.5,
      "ret5": 0.1036,
      "vol_surge": 0.07,
      "rsi14": 50.0,
      "score": 0.0878
    },
    {
      "ticker": "BAJAJ-AUTO.NS",
      "close": 8833.5,
      "ret5": 0.0777,
      "vol_surge": 0.12,
      "rsi14": 50.0,
      "score": 0.0703
    },
    {
      "ticker": "TATAMOTORS.NS",
      "close": 694.75,
      "ret5": 0.0621,
      "vol_surge": 0.09,
      "rsi14": 50.0,
      "score": 0.0557
    },
    {
      "ticker": "BHARTIARTL.NS",
      "close": 1945.5,
      "ret5": 0.0515,
      "vol_surge": 0.19,
      "rsi14": 50.0,
      "score": 0.0539
    }
  ]
}