{
  "as_of_ist": "2026-04-20T06:00:01.134937Z",
  "universe": "NIFTY50",
  "method": "momentum + volume (stable fallback)",
  "picks": [
    {
      "ticker": "ADANIPORTS.NS",
      "close": 1581.5,
      "ret5": 0.072,
      "vol_surge": 0.24,
      "rsi14": 50.0,
      "score": 0.0736
    },
    {
      "ticker": "ADANIENT.NS",
      "close": 2227.0,
      "ret5": 0.0672,
      "vol_surge": 0.2,
      "rsi14": 50.0,
      "score": 0.0671
    },
    {
      "ticker": "POWERGRID.NS",
      "close": 320.1,
      "ret5": 0.0573,
      "vol_surge": 0.17,
      "rsi14": 50.0,
      "score": 0.057
    },
    {
      "ticker": "ICICIBANK.NS",
      "close": 1373.0,
      "ret5": 0.0387,
      "vol_surge": 0.38,
      "rsi14": 50.0,
      "score": 0.0565
    },
    {
      "ticker": "SBIN.NS",
      "close": 1107.35,
      "ret5": 0.0381,
      "vol_surge": 0.32,
      "rsi14": 50.0,
      "score": 0.0515
    }
  ]
}