{
  "as_of_ist": "2026-02-06T05:02:09.916832Z",
  "universe": "NIFTY50",
  "method": "momentum + volume (stable fallback)",
  "picks": [
    {
      "ticker": "IOC.NS",
      "close": 176.2,
      "ret5": 0.0794,
      "vol_surge": 1.3,
      "rsi14": 50.0,
      "score": 0.1502
    },
    {
      "ticker": "POWERGRID.NS",
      "close": 291.55,
      "ret5": 0.1366,
      "vol_surge": 0.44,
      "rsi14": 50.0,
      "score": 0.1384
    },
    {
      "ticker": "ADANIPORTS.NS",
      "close": 1551.8,
      "ret5": 0.093,
      "vol_surge": 0.88,
      "rsi14": 50.0,
      "score": 0.1331
    },
    {
      "ticker": "HEROMOTOCO.NS",
      "close": 5798.0,
      "ret5": 0.0477,
      "vol_surge": 0.76,
      "rsi14": 50.0,
      "score": 0.0885
    },
    {
      "ticker": "ADANIENT.NS",
      "close": 2220.1,
      "ret5": 0.0988,
      "vol_surge": 0.14,
      "rsi14": 50.0,
      "score": 0.0884
    }
  ]
}